Metadata-Version: 2.1
Name: ascraper
Version: 1.2.1
Summary: An Module For Web Scraper.
Author: Abhay Sakariya
